rasterfairy/__init__.py
rasterfairy/coonswarp.py
rasterfairy/prime.py
rasterfairy/rasterfairy.py
rasterfairy/rfoptimizer.py
rasterfairy/utils.py
sjaandi/__init__.py
sjaandi/data/__init__.py
sjaandi/data/get_imagenette.py
sjaandi/usecases/__init__.py
sjaandi/usecases/mvp.py
sjaandi-0.1.6.dist-info/LICENSE
sjaandi-0.1.6.dist-info/METADATA
sjaandi-0.1.6.dist-info/WHEEL
sjaandi-0.1.6.dist-info/top_level.txt
sjaandi-0.1.6.dist-info/RECORD
