Metadata-Version: 2.1
Name: sjaandi
Version: 0.1.6
Summary: Library for visual similarity search and visualization
Home-page: https://github.com/pechyonkin/sjaandi
Author: Max Pechyonkin
Author-email: maxim.pechyonkin@gmail.com
License: MIT
Platform: UNKNOWN
Classifier: Programming Language :: Python :: 3
Classifier: License :: OSI Approved :: MIT License
Classifier: Operating System :: OS Independent
Requires-Dist: torch (>=1.2.0)
Requires-Dist: torchvision (>=0.4.0)
Requires-Dist: fastai (>=1.0.57)
Requires-Dist: matplotlib
Requires-Dist: numpy
Requires-Dist: scikit-learn
Requires-Dist: python-dotenv
Requires-Dist: click
Requires-Dist: rasterfairy-py3
